Workbook

Sheet Ingredientes
A1: Ingrediente | B1: Unidade | C1: Preço por Unidade (R$) | D1: Qtd Comprada | E1: Data Compra | F1: Saldo Inicial | G1: Saldo Restante | H1: Observações
A2: Açúcar | B2: kg | C2: 5.5 | D2: 2 | E2: 20/11/2025 | F2: =D2 -> 2 | G2: =F2 -> 2
A3: Farinha de Trigo | B3: kg | C3: 4.2 | D3: 1 | E3: 20/11/2025 | F3: =D3 -> 1 | G3: =F3 -> 1
A4: Chocolate em Pó | B4: kg | C4: 22 | D4: 0.5 | E4: 18/11/2025 | F4: =D4 -> 0.5 | G4: =F4 -> 0.5
A5: Leite Condensado | B5: L | C5: 12 | D5: 1 | E5: 20/11/2025 | F5: =D5 -> 1 | G5: =F5 -> 1
A6: Manteiga | B6: kg | C6: 18.5 | D6: 0.5 | E6: 19/11/2025 | F6: =D6 -> 0.5 | G6: =F6 -> 0.5
F7: =D7 -> 0 | G7: =F7 -> 0
F8: =D8 -> 0 | G8: =F8 -> 0
F9: =D9 -> 0 | G9: =F9 -> 0
F10: =D10 -> 0 | G10: =F10 -> 0
F11: =D11 -> 0 | G11: =F11 -> 0
F12: =D12 -> 0 | G12: =F12 -> 0
F13: =D13 -> 0 | G13: =F13 -> 0
F14: =D14 -> 0 | G14: =F14 -> 0
F15: =D15 -> 0 | G15: =F15 -> 0
F16: =D16 -> 0 | G16: =F16 -> 0
A18: ℹ️ COMO UTILIZAR ESTA ABA
A19: INSTRUÇÕES GERAIS:
A20: 1. Registre cada ingrediente | D20: Ex: Açúcar, Farinha, Chocolate
A21: 2. Informe unidade de medida | D21: kg, L, g, ml, unidade, etc
A22: 3. Digite preço pago/unidade | D22: Ex: 5,50 por kg de açúcar
A23: 4. Quantidade comprada = saldo | D23: Coluna Saldo Inicial
A24: 5. Conforme usa, saldo diminui | D24: Use nos cálculos de custo
A26: EXEMPLO PRÁTICO:
A27: Comprou 2kg de açúcar | D27: 2kg × R$ 5,50 = R$ 11,00
A28: Usou 200g em uma receita | D28: Saldo fica em 1,8 kg
A29: Custo do ingrediente usado | D29: 0,2kg × R$ 5,50 = R$ 1,10

Sheet Receitas Detalhadas
A1: 🍫 BRIGADEIRO
A2: Ingrediente Usado | B2: Unidade | C2: Quantidade Usada | D2: Preço Unitário (R$) | E2: Subtotal (R$)
A3: Açúcar | B3: g | C3: 200 | D3: =VLOOKUP(A3,Ingredientes!A:C,3,FALSE()) -> 5.5 | E3: =(C3/1000)*D3 -> 1.1
A4: Leite Condensado | B4: ml | C4: 150 | D4: =VLOOKUP(A4,Ingredientes!A:C,3,FALSE()) -> 12 | E4: =(C4/1000)*D4 -> 1.8
A5: Chocolate em Pó | B5: g | C5: 50 | D5: =VLOOKUP(A5,Ingredientes!A:C,3,FALSE()) -> 22 | E5: =(C5/1000)*D5 -> 1.1
A6: Manteiga | B6: g | C6: 20 | D6: =VLOOKUP(A6,Ingredientes!A:C,3,FALSE()) -> 18.5 | E6: =(C6/1000)*D6 -> 0.37
A15: TOTAL CUSTO | E15: =SUM(E3:E14) -> 4.37
A17: Preço de Venda: | B17: 80
A18: Quantidade Produzida: | B18: 20
A19: Custo Total do Lote: | B19: =E15 -> 4.37
A20: Lucro por Lote: | B20: =(B17*B18)-B19 -> 1595.63
A21: Lucro por Unidade: | B21: =B20/B18 -> 79.7815
A22: Margem de Lucro %: | B22: =((B20)/(B17*B18))*100 -> 99.726875
A24: ℹ️ COMO UTILIZAR ESTA ABA
A25: PASSO A PASSO:
A26: 1. Renomeie a aba para seu doce | C26: Ex: Brigadeiro → Beijinho
A27: 2. Liste ingredientes usados | C27: Coluna A
A28: 3. Coloque quantidade em GRAMAS | C28: Ex: 200g, não 0.2kg
A29: 4. Sistema busca preço automaticamente | C29: VLOOKUP dos Ingredientes
A30: 5. Subtotal = (Qtd / 1000) × Preço | C30: Automaticamente calculado
A31: 6. Informe Preço de Venda | C31: O valor que cobra por unidade
A32: 7. Quantidade produzida | C32: Quantas unidades saem do lote
A33: 8. Veja o lucro e margem% | C33: Automaticamente atualizado
A35: EXEMPLO:
A36: Receita: Brigadeiro
A37: Ingredientes: Açúcar, Leite Cond., Chocolate, Manteiga
A38: Quantidades: 200g, 150ml, 50g, 20g
A39: Total de custo: R$ 12,50
A40: Vende 20 unidades por R$ 80,00
A41: Lucro por lote: R$ 67,50
A42: Margem: 84% | C42: Excelente!

Sheet Resumo Receitas
A1: Receita | B1: Custo Total | C1: Preço Venda | D1: Quantidade | E1: Lucro Lote | F1: Lucro Unit | G1: Margem %
A2: Brigadeiro | B2: ='Receitas Detalhadas'!B19 -> 4.37 | C2: ='Receitas Detalhadas'!B17 -> 80 | D2: ='Receitas Detalhadas'!B18 -> 20 | E2: ='Receitas Detalhadas'!B20 -> 1595.63 | F2: ='Receitas Detalhadas'!B21 -> 79.7815 | G2: ='Receitas Detalhadas'!B22 -> 99.726875
A13: ℹ️ COMO UTILIZAR ESTA ABA
A14: VISÃO GERAL DE TODAS AS RECEITAS:
A15: Esta aba consolida automaticamente | D15: dados de todas as receitas
A17: COMO FUNCIONA:
A18: • Cada receita criada aparece aqui | D18: Automaticamente atualizada
A19: • Compara custo vs preço | D19: Mostra o melhor lucro
A20: • Margem% indica rentabilidade | D20: Acima de 50% é ótimo!
A22: PARA CRIAR NOVA RECEITA:
A23: 1. Vá à aba 'Receitas Detalhadas'
A24: 2. Clique botão direito na aba
A25: 3. Mover/Copiar → Copiar
A26: 4. Renomeie: 'Receita 1', 'Receita 2', etc
A27: 5. Edite os dados (ingredientes, preços)
A28: 6. Aqui aparecerá automaticamente
A30: EXEMPLO DE LEITURA:
A31: Brigadeiro: R$12,50 custo → R$80 venda | D31: Lucro R$67,50
A32: Produz 20 unidades por lote | D32: 84% de margem!

Sheet Análise
A1: ANÁLISE GERAL
A3: Ingredientes Cadastrados: | B3: =COUNTA(Ingredientes!A2:A16) -> 5
A4: Receitas Registradas: | B4: =COUNTA('Resumo Receitas'!A2:A11) -> 1
A5: Lucro Total: | B5: =SUM('Resumo Receitas'!E2:E11) -> 1595.63
A6: Margem Média: | B6: =AVERAGE('Resumo Receitas'!G2:G11) -> 99.726875
A8: 💡 RESUMO DE USO:
A9: ✓ Aba 1: Ingredientes - Registre todas compras
A10: ✓ Aba 2: Receitas - Crie uma por doce/produto
A11: ✓ Aba 3: Resumo - Veja tudo junto
A12: ✓ Aba 4: Análise - Acompanhe totais
A14: 📌 DICA IMPORTANTE:
A15: Copie a aba 'Receitas Detalhadas' para cada
A16: nova receita. Sistema puxará automaticamente
A17: os preços da aba Ingredientes via VLOOKUP
A19: 🎯 FÓRMULA CHAVE:
A20: Custo do ingrediente = (Qtd em g / 1000) × Preço/kg
A21: Margem % = (Lucro Total / Receita Total) × 100
... A26: • Margem <30% = Revisar preço
